MANIFEST.in
setup.py
gae_django/__init__.py
gae_django/mail.py
gae_django/memcached_backend.py
gae_django/stdlib_socket.py
gae_django.egg-info/PKG-INFO
gae_django.egg-info/SOURCES.txt
gae_django.egg-info/dependency_links.txt
gae_django.egg-info/not-zip-safe
gae_django.egg-info/top_level.txt
gae_django/errors/__init__.py
gae_django/errors/middleware.py
gae_django/errors/templates/capability-disabled.json
gae_django/errors/templates/deadline-exceeded.json
gae_django/errors/templates/internal-error.json
gae_django/errors/templates/taskqueue-internal-error.json
gae_django/errors/templates/timeout.json
gae_django/errors/templates/transaction-failed.json
gae_django/errors/templates/transient-error.json
gae_django/storage/__init__.py
gae_django/storage/googleCloud.py
gae_django/storage/cloudstorage/__init__.py
gae_django/storage/cloudstorage/api_utils.py
gae_django/storage/cloudstorage/cloudstorage_api.py
gae_django/storage/cloudstorage/common.py
gae_django/storage/cloudstorage/errors.py
gae_django/storage/cloudstorage/rest_api.py
gae_django/storage/cloudstorage/storage_api.py
gae_django/storage/cloudstorage/test_utils.py