Metadata-Version: 1.0
Name: gae-django
Version: 0.6
Summary: helpers for Django project running on Google App Engine
Home-page: https://gitlab.com/taelimoh/gae-django
Author: Tae-lim Oh
Author-email: taelimoh@gmail.com
License: MIT
Keywords: django googleappengine gae
Platform: UNKNOWN
